Metadata-Version: 2.1
Name: drf-firebase-auth-fjcg
Version: 1.0.1
Summary: Custom Django Rest Framework authentication backend for parsing Firebase uid tokens and storing as local users.
Home-page: https://github.com/romulus85/drf-firebase-auth.git
Author: Fran Castaño
Author-email: djlargo50@gmail.com
License: MIT
Keywords: drf,django,rest_framework,djangorestframework,authentication,python3,firebase
Classifier: Environment :: Web Environment
Classifier: Framework :: Django
Classifier: Intended Audience :: Developers
Classifier: License :: OSI Approved :: MIT License
Classifier: Operating System :: OS Independent
Classifier: Programming Language :: Python :: 3
Classifier: Topic :: Internet :: WWW/HTTP
Requires-Python: >=3.4
License-File: LICENSE
Requires-Dist: djangorestframework >=3.9
Requires-Dist: firebase-admin >=4.5
